aiida_firecrest/__init__.py
aiida_firecrest/scheduler.py
aiida_firecrest/transport.py
aiida_firecrest/utils.py
aiida_firecrest-1.0.0.dist-info/entry_points.txt
aiida_firecrest-1.0.0.dist-info/licenses/LICENSE
aiida_firecrest-1.0.0.dist-info/WHEEL
aiida_firecrest-1.0.0.dist-info/METADATA
aiida_firecrest-1.0.0.dist-info/RECORD
