Metadata-Version: 2.4
Name: aiida_firecrest
Version: 1.0.0
Summary: AiiDA Transport/Scheduler plugins for interfacing with FirecREST.
Keywords: aiida,firecrest
Author: AiiDA team
Requires-Python: >=3.9
Classifier: Development Status :: 3 - Alpha
Classifier: Framework :: AiiDA
Classifier: License :: OSI Approved :: MIT License
Classifier: Operating System :: MacOS :: MacOS X
Classifier: Operating System :: POSIX :: Linux
Classifier: Programming Language :: Python :: 3
Classifier: Programming Language :: Python :: 3.9
Classifier: Programming Language :: Python :: 3.10
Classifier: Programming Language :: Python :: 3.11
Classifier: Programming Language :: Python :: 3.12
Classifier: Programming Language :: Python :: 3.13
Classifier: Programming Language :: Python :: Implementation :: CPython
Classifier: Topic :: Software Development :: Libraries :: Python Modules
License-File: LICENSE
Requires-Dist: aiida-core>=2.7.0
Requires-Dist: click
Requires-Dist: pyfirecrest>=3.6.0
Requires-Dist: pyyaml
Requires-Dist: pytest ; extra == "dev"
Requires-Dist: pytest-cov ; extra == "dev"
Requires-Dist: pytest-regressions ; extra == "dev"
Requires-Dist: pytest-timeout ; extra == "dev"
Requires-Dist: pytest-asyncio ; extra == "dev"
Requires-Dist: pgtest ; extra == "dev"
Requires-Dist: furo==2024.8.6 ; extra == "docs"
Project-URL: Home, http://github.com/aiidateam/aiida-firecrest
Provides-Extra: dev
Provides-Extra: docs
